pyz80/pyz80.py
pyz80-1.3.0.dist-info/licenses/COPYING
pyz80-1.3.0.dist-info/METADATA
pyz80-1.3.0.dist-info/WHEEL
pyz80-1.3.0.dist-info/entry_points.txt
pyz80-1.3.0.dist-info/top_level.txt
pyz80-1.3.0.dist-info/RECORD
