Metadata-Version: 2.4
Name: pyz80
Version: 1.3.0
Summary: Z80 cross-assembler for SAM Coupé code
Author-email: Andrew Collier <andrew@intensity.org.uk>, Simon Owen <simon@simonowen.com>, Adrian Brown <adrian@apbcomputerservices.co.uk>, Stefan Drissen <stefan.drissen@gmail.com>
License-Expression: GPL-2.0-or-later
Project-URL: Homepage, https://github.com/simonowen/pyz80
Keywords: sam,coupe,z80,assembler
Classifier: Development Status :: 5 - Production/Stable
Classifier: Programming Language :: Python :: 3.8
Classifier: Topic :: Software Development :: Assemblers
Classifier: Topic :: Utilities
Classifier: Environment :: Console
License-File: COPYING
Dynamic: license-file
